steamCloudSaveDownloader/__init__.py
steamCloudSaveDownloader/__main__.py
steamCloudSaveDownloader/args.py
steamCloudSaveDownloader/auth.py
steamCloudSaveDownloader/config.py
steamCloudSaveDownloader/db.py
steamCloudSaveDownloader/err.py
steamCloudSaveDownloader/notifier.py
steamCloudSaveDownloader/parser.py
steamCloudSaveDownloader/storage.py
steamCloudSaveDownloader/stored.py
steamCloudSaveDownloader/summary.py
steamCloudSaveDownloader/utility.py
steamCloudSaveDownloader/ver.py
steamCloudSaveDownloader/web.py
scsd-0.0.84.dist-info/METADATA
scsd-0.0.84.dist-info/WHEEL
scsd-0.0.84.dist-info/entry_points.txt
scsd-0.0.84.dist-info/licenses/LICENSE
scsd-0.0.84.dist-info/RECORD
