Metadata-Version: 2.4
Name: scsd
Version: 0.0.84
Summary: Steam Cloud Save Downloader
Project-URL: Homepage, https://github.com/hhhhhojeihsu/steamCloudSaveDownloader
Project-URL: Bug Tracker, https://github.com/hhhhhojeihsu/steamCloudSaveDownloader/issues
Author: hchsu
License-File: LICENSE
Classifier: License :: OSI Approved :: MIT License
Classifier: Operating System :: OS Independent
Classifier: Programming Language :: Python :: 3
Requires-Python: >=3.12
Requires-Dist: beautifulsoup4<5,>=4.12.2
Requires-Dist: discord-webhook<2,>=1.1.0
Requires-Dist: requests<3,>=2.28.2
Requires-Dist: steampy<2,>=1.2.0
Requires-Dist: tzdata>=2023.3
